enamlnativecli/__init__.py
enamlnativecli/__init__.pyc
enamlnativecli/main.py
enamlnativecli/main.pyc
enamlnativecli/__pycache__/__init__.cpython-310.pyc
enamlnativecli/__pycache__/__init__.cpython-36.pyc
enamlnativecli/__pycache__/__init__.cpython-37.pyc
enamlnativecli/__pycache__/__init__.cpython-39.pyc
enamlnativecli/__pycache__/__main__.cpython-37.pyc
enamlnativecli/__pycache__/main.cpython-310.pyc
enamlnativecli/__pycache__/main.cpython-36.pyc
enamlnativecli/__pycache__/main.cpython-37.pyc
enamlnativecli/__pycache__/main.cpython-39.pyc
enamlnativecli/templates/android-lib/cookiecutter.json
enamlnativecli/templates/android-lib/{{cookiecutter.project_name}}/README.md
enamlnativecli/templates/android-lib/{{cookiecutter.project_name}}/build.sh
enamlnativecli/templates/android-lib/{{cookiecutter.project_name}}/meta.yaml
enamlnativecli/templates/android-lib/{{cookiecutter.project_name}}/android/.gitignore
enamlnativecli/templates/android-lib/{{cookiecutter.project_name}}/android/build.gradle
enamlnativecli/templates/android-lib/{{cookiecutter.project_name}}/android/gradlew
enamlnativecli/templates/android-lib/{{cookiecutter.project_name}}/android/gradlew.bat
enamlnativecli/templates/android-lib/{{cookiecutter.project_name}}/android/proguard-rules.pro
enamlnativecli/templates/android-lib/{{cookiecutter.project_name}}/android/gradle/wrapper/gradle-wrapper.jar
enamlnativecli/templates/android-lib/{{cookiecutter.project_name}}/android/gradle/wrapper/gradle-wrapper.properties
enamlnativecli/templates/android-lib/{{cookiecutter.project_name}}/android/src/main/AndroidManifest.xml
enamlnativecli/templates/android-lib/{{cookiecutter.project_name}}/android/src/main/java/{{cookiecutter.bundle_path}}/{{cookiecutter.widget_name}}Package.java
enamlnativecli/templates/android-lib/{{cookiecutter.project_name}}/{{cookiecutter.project_package}}/__init__.py
enamlnativecli/templates/android-lib/{{cookiecutter.project_name}}/{{cookiecutter.project_package}}/android/__init__.py
enaml_native_cli-3.0.0.dist-info/LICENSE
enaml_native_cli-3.0.0.dist-info/METADATA
enaml_native_cli-3.0.0.dist-info/WHEEL
enaml_native_cli-3.0.0.dist-info/entry_points.txt
enaml_native_cli-3.0.0.dist-info/top_level.txt
enaml_native_cli-3.0.0.dist-info/RECORD
