Metadata-Version: 2.1
Name: enaml-native-cli
Version: 3.0.0
Summary: Build native mobile apps in python
Home-page: https://codelv.com/projects//enaml-native
Author: CodeLV
Author-email: info@codelv.com
License: GPLv3
Platform: UNKNOWN
License-File: LICENSE
Requires-Dist: sh
Requires-Dist: atom
Requires-Dist: ruamel.yaml
Requires-Dist: cookiecutter
Requires-Dist: pbs
